{
  "config": {
    "data_dir": "data/processed_selected_2020_2022",
    "time_col": null,
    "target_col": "Active_Pow",
    "feature_cols": [
      "Active_Pow",
      "Radiation_Global_Tilted",
      "Radiation_Diffuse_Tilted",
      "Weather_T",
      "Weather_R",
      "solar_elevation",
      "sin_time_of_day",
      "cos_time_of_day",
      "sin_day_of_year",
      "cos_day_of_year",
      "day_night_label"
    ],
    "seq_len": 96,
    "pred_len": 12,
    "sampling_freq_minutes": null,
    "d_model": 128,
    "n_heads": 4,
    "e_layers": 2,
    "d_ff": 512,
    "factor": 5,
    "activation": "gelu",
    "disable_norm": false,
    "output_attention": false,
    "dropout": 0.1,
    "epochs": 120,
    "batch_size": 128,
    "learning_rate": 0.001,
    "weight_decay": 1e-05,
    "grad_clip": 1.0,
    "patience": 20,
    "min_delta": 1e-05,
    "num_workers": 2,
    "log_interval": 0,
    "progress_mininterval": 15.0,
    "seed": 42,
    "device": "cuda",
    "results_dir": "results/tuning/itransformer/standard/pred_len_12/s2_ff4x_pl12_lr0p001_bs128_dm128_ff512_el2_do0p1_wd1e-05_actgelu_nh4_fac5",
    "checkpoint_path": "checkpoints/tuning/itransformer/standard/pred_len_12/s2_ff4x_pl12_lr0p001_bs128_dm128_ff512_el2_do0p1_wd1e-05_actgelu_nh4_fac5/best_model.pth",
    "eval_checkpoint_path": null,
    "report_split": "validation",
    "experiment_name": "s2_ff4x_pl12_lr0p001_bs128_dm128_ff512_el2_do0p1_wd1e-05_actgelu_nh4_fac5",
    "tuning_stage": "s2",
    "tuning_only": true,
    "max_train_batches": null,
    "max_eval_batches": null
  },
  "experiment_name": "s2_ff4x_pl12_lr0p001_bs128_dm128_ff512_el2_do0p1_wd1e-05_actgelu_nh4_fac5",
  "tuning_stage": "s2",
  "device": "cuda",
  "baseline_type": "itransformer",
  "baseline_definition": "Vanilla iTransformer backbone with Active_Pow extracted from the multivariate forecast output.",
  "best_epoch": 46,
  "best_validation_loss": 0.06635957703320364,
  "expected_delta_minutes": 5.0,
  "dataset_summary": {
    "train": {
      "rows": 103619,
      "expected_delta_minutes": 5.0,
      "total_segments": 20,
      "usable_segments": 20,
      "dropped_segments": 0,
      "samples": 101479,
      "max_segment_length": 27447,
      "min_segment_length": 158,
      "max_usable_segment_length": 27447,
      "min_usable_segment_length": 158
    },
    "validation": {
      "rows": 47165,
      "expected_delta_minutes": 5.0,
      "total_segments": 11,
      "usable_segments": 11,
      "dropped_segments": 0,
      "samples": 45988,
      "max_segment_length": 16453,
      "min_segment_length": 143,
      "max_usable_segment_length": 16453,
      "min_usable_segment_length": 143
    },
    "calibration": {
      "rows": 51804,
      "expected_delta_minutes": 5.0,
      "total_segments": 18,
      "usable_segments": 16,
      "dropped_segments": 2,
      "samples": 50068,
      "max_segment_length": 16947,
      "min_segment_length": 2,
      "max_usable_segment_length": 16947,
      "min_usable_segment_length": 161
    }
  },
  "raw_split_rows": {
    "train": 103619,
    "validation": 47165,
    "calibration": 51804
  },
  "target_feature_index": 0,
  "trainable_parameter_count": 410764,
  "report_split": "validation",
  "calibration_usage": "loaded_but_unused",
  "validation_metrics": {
    "all_timestamps": {
      "count": 551856,
      "mae": 0.34089378776196744,
      "mse": 0.5259404439104236,
      "rmse": 0.7252175148949614,
      "mbe": -0.025230812069316984,
      "median_ae": 0.08489541709423065,
      "p95_ae": 1.6755621954798698,
      "max_ae": 9.452052816748619,
      "smape": 120.0880887552032,
      "mape_nonzero": 32.58752197914547,
      "wape": 15.886406811711499,
      "nmae_by_mean": 15.886406811711499,
      "nrmse_by_mean": 33.79674515114522,
      "nmbe_by_mean": -1.1758118191431859,
      "nmae_by_max": 3.6039731022215262,
      "nrmse_by_max": 7.667093126280136,
      "nmbe_by_max": -0.26674340017166365,
      "r2": 0.9330504134012619,
      "pearson_r": 0.9664615477055892,
      "mean_true": 2.1458205861293926,
      "mean_pred": 2.1205897740600776,
      "mean_abs_true": 2.1458205861293926,
      "max_abs_true": 9.458832740783691,
      "sum_abs_true": 1184183.965379022,
      "nonzero_target_count": 250032
    },
    "daytime_only": {
      "count": 250512,
      "mae": 0.6490520836238525,
      "mse": 1.0982080578595186,
      "rmse": 1.0479542250783278,
      "mbe": -0.05382640878673817,
      "median_ae": 0.32638001441955566,
      "p95_ae": 2.442574441432953,
      "max_ae": 9.452052816748619,
      "smape": 24.01267053416324,
      "mape_nonzero": 32.58752197914547,
      "wape": 13.730580748130347,
      "nmae_by_mean": 13.730580748130347,
      "nrmse_by_mean": 22.16928420820118,
      "nmbe_by_mean": -1.1386880511988247,
      "nmae_by_max": 6.861862360937325,
      "nrmse_by_max": 11.079107261933693,
      "nmbe_by_max": -0.5690597377269883,
      "r2": 0.7848310550782607,
      "pearson_r": 0.8937337779951764,
      "mean_true": 4.727054853176782,
      "mean_pred": 4.673228444390044,
      "mean_abs_true": 4.727054853176782,
      "max_abs_true": 9.458832740783691,
      "sum_abs_true": 1184183.965379022,
      "nonzero_target_count": 250032
    },
    "per_horizon_all": {
      "t+1": {
        "count": 45988,
        "mae": 0.2221193607590747,
        "mse": 0.2396929569624097,
        "rmse": 0.48958447377588443,
        "mbe": -0.010646464968593837,
        "median_ae": 0.06811787188053131,
        "p95_ae": 1.0420467138290406,
        "max_ae": 6.2151408195495605,
        "smape": 116.43580743442948,
        "mape_nonzero": 18.293203965575618,
        "wape": 10.348710163365988,
        "nmae_by_mean": 10.348710163365988,
        "nrmse_by_mean": 22.810113455558778,
        "nmbe_by_mean": -0.4960269102517021,
        "nmae_by_max": 2.3482745371039457,
        "nrmse_by_max": 5.175950217038312,
        "nmbe_by_max": -0.11255580112638451,
        "r2": 0.969492761374168,
        "pearson_r": 0.9847884363026422,
        "mean_true": 2.146348262272995,
        "mean_pred": 2.1357017973044012,
        "mean_abs_true": 2.146348262272995,
        "max_abs_true": 9.458832740783691,
        "sum_abs_true": 98706.2638854105,
        "nonzero_target_count": 20836
      },
      "t+2": {
        "count": 45988,
        "mae": 0.26476528569067137,
        "mse": 0.3399621499214325,
        "rmse": 0.5830627324065846,
        "mbe": -0.01004741365654503,
        "median_ae": 0.07655303180217743,
        "p95_ae": 1.2965894699096687,
        "max_ae": 7.452514290809631,
        "smape": 117.73937099587803,
        "mape_nonzero": 22.643133584872665,
        "wape": 12.336169661328464,
        "nmae_by_mean": 12.336169661328462,
        "nrmse_by_mean": 27.166555356387533,
        "nmbe_by_mean": -0.46813765332323987,
        "nmae_by_max": 2.7991327571432962,
        "nrmse_by_max": 6.164214426718747,
        "nmbe_by_max": -0.10622255337303461,
        "r2": 0.9567297533906927,
        "pearson_r": 0.9783483901582734,
        "mean_true": 2.146251980634313,
        "mean_pred": 2.136204566977768,
        "mean_abs_true": 2.146251980634313,
        "max_abs_true": 9.458832740783691,
        "sum_abs_true": 98701.83608541079,
        "nonzero_target_count": 20836
      },
      "t+3": {
        "count": 45988,
        "mae": 0.2924999344255182,
        "mse": 0.399851728049046,
        "rmse": 0.6323383018994232,
        "mbe": -0.01186072181933222,
        "median_ae": 0.08565092086791992,
        "p95_ae": 1.4242733418941502,
        "max_ae": 8.434280514717102,
        "smape": 118.60914180743387,
        "mape_nonzero": 25.668730730789452,
        "wape": 13.629061726072653,
        "nmae_by_mean": 13.629061726072656,
        "nrmse_by_mean": 29.46386215529811,
        "nmbe_by_mean": -0.5526514394232045,
        "nmae_by_max": 3.0923470415577277,
        "nrmse_by_max": 6.68516210433627,
        "nmbe_by_max": -0.12539308120115383,
        "r2": 0.9491054970315645,
        "pearson_r": 0.9746092939883078,
        "mean_true": 2.1461487247207947,
        "mean_pred": 2.1342880029014624,
        "mean_abs_true": 2.1461487247207947,
        "max_abs_true": 9.458832740783691,
        "sum_abs_true": 98697.08755245991,
        "nonzero_target_count": 20836
      },
      "t+4": {
        "count": 45988,
        "mae": 0.3117035760308293,
        "mse": 0.44087162737448277,
        "rmse": 0.6639816468656967,
        "mbe": -0.01553118750301131,
        "median_ae": 0.08982416987419128,
        "p95_ae": 1.5158710032701497,
        "max_ae": 8.62689220905304,
        "smape": 119.18380053741244,
        "mape_nonzero": 27.418011108400325,
        "wape": 14.524525752673407,
        "nmae_by_mean": 14.524525752673407,
        "nrmse_by_mean": 30.939710901005068,
        "nmbe_by_mean": -0.7237104422400841,
        "nmae_by_max": 3.2953704180311343,
        "nrmse_by_max": 7.019699629562156,
        "nmbe_by_max": -0.1641977179281902,
        "r2": 0.9438827825055461,
        "pearson_r": 0.9720291818372739,
        "mean_true": 2.1460499388316117,
        "mean_pred": 2.1305187513286006,
        "mean_abs_true": 2.1460499388316117,
        "max_abs_true": 9.458832740783691,
        "sum_abs_true": 98692.54458698817,
        "nonzero_target_count": 20836
      },
      "t+5": {
        "count": 45988,
        "mae": 0.3219851997611467,
        "mse": 0.47604585324417786,
        "rmse": 0.6899607621047575,
        "mbe": -0.0111923393503046,
        "median_ae": 0.07579080760478973,
        "p95_ae": 1.5856836795806888,
        "max_ae": 8.384565234184265,
        "smape": 119.60012913695392,
        "mape_nonzero": 30.115139155749794,
        "wape": 15.004431342467484,
        "nmae_by_mean": 15.004431342467484,
        "nrmse_by_mean": 32.15200230220826,
        "nmbe_by_mean": -0.5215602688192467,
        "nmae_by_max": 3.404069070519047,
        "nrmse_by_max": 7.294354187381395,
        "nmbe_by_max": -0.11832685551195488,
        "r2": 0.9394032473940727,
        "pearson_r": 0.9696203008085393,
        "mean_true": 2.1459340404979064,
        "mean_pred": 2.1347417011476013,
        "mean_abs_true": 2.1459340404979064,
        "max_abs_true": 9.458832740783691,
        "sum_abs_true": 98687.21465441771,
        "nonzero_target_count": 20836
      },
      "t+6": {
        "count": 45988,
        "mae": 0.33884271592635296,
        "mse": 0.5128769808684335,
        "rmse": 0.7161542996229469,
        "mbe": -0.018612245918356748,
        "median_ae": 0.07756070792675018,
        "p95_ae": 1.6727999016642587,
        "max_ae": 8.42754477262497,
        "smape": 120.14215024826169,
        "mape_nonzero": 32.49857937155497,
        "wape": 15.79068486984764,
        "nmae_by_mean": 15.79068486984764,
        "nrmse_by_mean": 33.374088720237694,
        "nmbe_by_mean": -0.867364403019241,
        "nmae_by_max": 3.582288906170878,
        "nrmse_by_max": 7.571275645197755,
        "nmbe_by_max": -0.19677106497619146,
        "r2": 0.9347135920368946,
        "pearson_r": 0.9671432511235671,
        "mean_true": 2.14583926358618,
        "mean_pred": 2.127227017667823,
        "mean_abs_true": 2.14583926358618,
        "max_abs_true": 9.458832740783691,
        "sum_abs_true": 98682.85605380125,
        "nonzero_target_count": 20836
      },
      "t+7": {
        "count": 45988,
        "mae": 0.3525632355838088,
        "mse": 0.5517959709744997,
        "rmse": 0.7428297052316228,
        "mbe": -0.020962778489489017,
        "median_ae": 0.07826252281665802,
        "p95_ae": 1.742873154580593,
        "max_ae": 8.969415485858917,
        "smape": 120.57942962828014,
        "mape_nonzero": 34.649428047383786,
        "wape": 16.43061179827782,
        "nmae_by_mean": 16.43061179827782,
        "nrmse_by_mean": 34.6183188915868,
        "nmbe_by_mean": -0.9769347476169477,
        "nmae_by_max": 3.727344010045344,
        "nrmse_by_max": 7.853291474631543,
        "nmbe_by_max": -0.22162119855554385,
        "r2": 0.9297599535352317,
        "pearson_r": 0.9647689576913887,
        "mean_true": 2.1457705891436305,
        "mean_pred": 2.1248078106541413,
        "mean_abs_true": 2.1457705891436305,
        "max_abs_true": 9.458832740783691,
        "sum_abs_true": 98679.69785353728,
        "nonzero_target_count": 20836
      },
      "t+8": {
        "count": 45988,
        "mae": 0.3671346083754966,
        "mse": 0.5895937630693453,
        "rmse": 0.7678500915343732,
        "mbe": -0.02326421548254413,
        "median_ae": 0.08276832103729248,
        "p95_ae": 1.8029488086700447,
        "max_ae": 9.10402326285839,
        "smape": 120.9123235440485,
        "mape_nonzero": 36.33113266951432,
        "wape": 17.110369186976314,
        "nmae_by_mean": 17.11036918697631,
        "nrmse_by_mean": 35.785780601128295,
        "nmbe_by_mean": -1.0842326129727728,
        "nmae_by_max": 3.881394443021713,
        "nrmse_by_max": 8.117810226452473,
        "nmbe_by_max": -0.24595228734974572,
        "r2": 0.9249472702323038,
        "pearson_r": 0.9623876636470085,
        "mean_true": 2.1456849023160993,
        "mean_pred": 2.122420686833555,
        "mean_abs_true": 2.1456849023160993,
        "max_abs_true": 9.458832740783691,
        "sum_abs_true": 98675.75728771277,
        "nonzero_target_count": 20836
      },
      "t+9": {
        "count": 45988,
        "mae": 0.38018792209846236,
        "mse": 0.6243604254782129,
        "rmse": 0.7901648090608775,
        "mbe": -0.03456206402336513,
        "median_ae": 0.08680637180805206,
        "p95_ae": 1.852798950672151,
        "max_ae": 9.149853572249413,
        "smape": 121.2295002883222,
        "mape_nonzero": 37.791337217115654,
        "wape": 17.719418114611095,
        "nmae_by_mean": 17.719418114611095,
        "nrmse_by_mean": 36.82721048559622,
        "nmbe_by_mean": -1.6108340842436286,
        "nmae_by_max": 4.019395759681894,
        "nrmse_by_max": 8.353724298918198,
        "nmbe_by_max": -0.36539459963536225,
        "r2": 0.9205196926104795,
        "pearson_r": 0.9600221788406602,
        "mean_true": 2.1456004911637963,
        "mean_pred": 2.111038427140431,
        "mean_abs_true": 2.1456004911637963,
        "max_abs_true": 9.458832740783691,
        "sum_abs_true": 98671.87538764067,
        "nonzero_target_count": 20836
      },
      "t+10": {
        "count": 45988,
        "mae": 0.3958041065423872,
        "mse": 0.6656770015211455,
        "rmse": 0.8158903121873341,
        "mbe": -0.033548834392092775,
        "median_ae": 0.0964319258928299,
        "p95_ae": 1.9392381608486176,
        "max_ae": 9.187969341874123,
        "smape": 121.67355968670105,
        "mape_nonzero": 40.00722253651999,
        "wape": 18.448081287577583,
        "nmae_by_mean": 18.448081287577583,
        "nrmse_by_mean": 38.02792985768856,
        "nmbe_by_mean": -1.5636816640822948,
        "nmae_by_max": 4.184492076234701,
        "nrmse_by_max": 8.625697636765011,
        "nmbe_by_max": -0.3546826052588933,
        "r2": 0.9152555993077105,
        "pearson_r": 0.9573409830826033,
        "mean_true": 2.1455028323672365,
        "mean_pred": 2.111953997975143,
        "mean_abs_true": 2.1455028323672365,
        "max_abs_true": 9.458832740783691,
        "sum_abs_true": 98667.38425490446,
        "nonzero_target_count": 20836
      },
      "t+11": {
        "count": 45988,
        "mae": 0.4121485652193041,
        "mse": 0.7107707254331187,
        "rmse": 0.8430721946744055,
        "mbe": -0.04727969345278535,
        "median_ae": 0.09739001095294952,
        "p95_ae": 2.031183815002442,
        "max_ae": 9.294675841927528,
        "smape": 122.19920634705078,
        "mape_nonzero": 41.98087004416502,
        "wape": 19.21084032329092,
        "nmae_by_mean": 19.21084032329092,
        "nrmse_by_mean": 39.29681352712823,
        "nmbe_by_mean": -2.2037748474808003,
        "nmae_by_max": 4.357287801931852,
        "nrmse_by_max": 8.913068005096731,
        "nmbe_by_max": -0.4998470186382436,
        "r2": 0.9095093419347605,
        "pearson_r": 0.9545769758337588,
        "mean_true": 2.145395819669698,
        "mean_pred": 2.0981161262169126,
        "mean_abs_true": 2.145395819669698,
        "max_abs_true": 9.458832740783691,
        "sum_abs_true": 98662.46295497008,
        "nonzero_target_count": 20836
      },
      "t+12": {
        "count": 45988,
        "mae": 0.4309709427305568,
        "mse": 0.7597861440287803,
        "rmse": 0.8716571252670285,
        "mbe": -0.06526178577538362,
        "median_ae": 0.10641534626483917,
        "p95_ae": 2.114285838603974,
        "max_ae": 9.452052816748619,
        "smape": 122.7526454076665,
        "mape_nonzero": 43.65347531810412,
        "wape": 20.088886734540775,
        "nmae_by_mean": 20.088886734540775,
        "nrmse_by_mean": 40.630630802857645,
        "nmbe_by_mean": -3.042053402090281,
        "nmae_by_max": 4.556280405216782,
        "nrmse_by_max": 9.215271579004677,
        "nmbe_by_max": -0.6899560185052653,
        "r2": 0.9032637439506359,
        "pearson_r": 0.9519006006377184,
        "mean_true": 2.145320188348449,
        "mean_pred": 2.0800584025730653,
        "mean_abs_true": 2.145320188348449,
        "max_abs_true": 9.458832740783691,
        "sum_abs_true": 98658.98482176848,
        "nonzero_target_count": 20836
      }
    },
    "per_horizon_daytime": {
      "t+1": {
        "count": 20876,
        "mae": 0.4190072853721092,
        "mse": 0.5071389368223871,
        "rmse": 0.7121368806784178,
        "mbe": 0.010936700260222674,
        "median_ae": 0.20778656005859375,
        "p95_ae": 1.605574607849121,
        "max_ae": 6.2151408195495605,
        "smape": 15.966491775331118,
        "mape_nonzero": 18.293203965575618,
        "wape": 8.861844978331765,
        "nmae_by_mean": 8.861844978331765,
        "nrmse_by_mean": 15.061424610601676,
        "nmbe_by_mean": 0.23130705757180933,
        "nmae_by_max": 4.429799076216599,
        "nrmse_by_max": 7.5288029738372915,
        "nmbe_by_max": 0.11562420607213884,
        "r2": 0.9005701713934109,
        "pearson_r": 0.949658310644502,
        "mean_true": 4.728217277515353,
        "mean_pred": 4.739153977775575,
        "mean_abs_true": 4.728217277515353,
        "max_abs_true": 9.458832740783691,
        "sum_abs_true": 98706.2638854105,
        "nonzero_target_count": 20836
      },
      "t+2": {
        "count": 20876,
        "mae": 0.5038663900838779,
        "mse": 0.7203653871382947,
        "rmse": 0.8487434165507822,
        "mbe": -0.0005171155979022423,
        "median_ae": 0.24351632595062256,
        "p95_ae": 1.9336585998535156,
        "max_ae": 7.452514290809631,
        "smape": 18.819874433991547,
        "mape_nonzero": 22.643133584872665,
        "wape": 10.65706087806589,
        "nmae_by_mean": 10.657060878065892,
        "nrmse_by_mean": 17.951406241907893,
        "nmbe_by_mean": -0.010937289162954968,
        "nmae_by_max": 5.326940478726883,
        "nrmse_by_max": 8.973024894406382,
        "nmbe_by_max": -0.00546701281303551,
        "r2": 0.8587829124766846,
        "pearson_r": 0.9284070654149341,
        "mean_true": 4.728005177496206,
        "mean_pred": 4.7274880618983035,
        "mean_abs_true": 4.728005177496206,
        "max_abs_true": 9.458832740783691,
        "sum_abs_true": 98701.83608541079,
        "nonzero_target_count": 20836
      },
      "t+3": {
        "count": 20876,
        "mae": 0.5531906242550052,
        "mse": 0.846905842909092,
        "rmse": 0.9202748735617484,
        "mbe": 0.002126734537498704,
        "median_ae": 0.2664567232131958,
        "p95_ae": 2.1074156761169434,
        "max_ae": 8.434280514717102,
        "smape": 20.731472217970342,
        "mape_nonzero": 25.668730730789452,
        "wape": 11.7008594258764,
        "nmae_by_mean": 11.700859425876398,
        "nrmse_by_mean": 19.465273734915016,
        "nmbe_by_mean": 0.044983809862904484,
        "nmae_by_max": 5.848402645601404,
        "nrmse_by_max": 9.729264686051538,
        "nmbe_by_max": 0.02248411189605725,
        "r2": 0.8339977442151933,
        "pearson_r": 0.9161992225091784,
        "mean_true": 4.727777713760295,
        "mean_pred": 4.729904448297793,
        "mean_abs_true": 4.727777713760295,
        "max_abs_true": 9.458832740783691,
        "sum_abs_true": 98697.08755245991,
        "nonzero_target_count": 20836
      },
      "t+4": {
        "count": 20876,
        "mae": 0.5880562554339421,
        "mse": 0.9317673259419361,
        "rmse": 0.965280956997462,
        "mbe": -0.005219138783295248,
        "median_ae": 0.29205989837646484,
        "p95_ae": 2.202492117881775,
        "max_ae": 8.62689220905304,
        "smape": 21.992021793201637,
        "mape_nonzero": 27.418011108400325,
        "wape": 12.43889539966072,
        "nmae_by_mean": 12.43889539966072,
        "nrmse_by_mean": 20.41816364408117,
        "nmbe_by_mean": -0.11039814779933886,
        "nmae_by_max": 6.217006596368042,
        "nrmse_by_max": 10.205074806275576,
        "nmbe_by_max": -0.05517740852728967,
        "r2": 0.8173870096219722,
        "pearson_r": 0.9082534234443906,
        "mean_true": 4.727560097096578,
        "mean_pred": 4.722340958313283,
        "mean_abs_true": 4.727560097096578,
        "max_abs_true": 9.458832740783691,
        "sum_abs_true": 98692.54458698817,
        "nonzero_target_count": 20836
      },
      "t+5": {
        "count": 20876,
        "mae": 0.6180898432043754,
        "mse": 1.0044803316620616,
        "rmse": 1.002237662264825,
        "mbe": -0.020440783952041294,
        "median_ae": 0.30850958824157715,
        "p95_ae": 2.3009897470474243,
        "max_ae": 8.384565234184265,
        "smape": 22.92765826557724,
        "mape_nonzero": 30.115139155749794,
        "wape": 13.074888790730432,
        "nmae_by_mean": 13.074888790730432,
        "nrmse_by_mean": 21.201037551528348,
        "nmbe_by_mean": -0.43239826686476646,
        "nmae_by_max": 6.534525560848061,
        "nrmse_by_max": 10.595785862070194,
        "nmbe_by_max": -0.21610260496421163,
        "r2": 0.8031616605296605,
        "pearson_r": 0.9010194385337532,
        "mean_true": 4.727304783216024,
        "mean_pred": 4.706863999263982,
        "mean_abs_true": 4.727304783216024,
        "max_abs_true": 9.458832740783691,
        "sum_abs_true": 98687.21465441771,
        "nonzero_target_count": 20836
      },
      "t+6": {
        "count": 20876,
        "mae": 0.6511285194133138,
        "mse": 1.0794202258902335,
        "rmse": 1.0389515031464334,
        "mbe": -0.0494450901627106,
        "median_ae": 0.33936265110969543,
        "p95_ae": 2.39077827334404,
        "max_ae": 8.42754477262497,
        "smape": 24.113595254788798,
        "mape_nonzero": 32.49857937155497,
        "wape": 13.774387482119026,
        "nmae_by_mean": 13.77438748211903,
        "nrmse_by_mean": 21.97864193134029,
        "nmbe_by_mean": -1.0459929348558672,
        "nmae_by_max": 6.883814707980195,
        "nrmse_by_max": 10.983929324247182,
        "nmbe_by_max": -0.5227398720089211,
        "r2": 0.7885062151669776,
        "pearson_r": 0.8940548985695511,
        "mean_true": 4.7270959979786,
        "mean_pred": 4.677650907815889,
        "mean_abs_true": 4.7270959979786,
        "max_abs_true": 9.458832740783691,
        "sum_abs_true": 98682.85605380125,
        "nonzero_target_count": 20836
      },
      "t+7": {
        "count": 20876,
        "mae": 0.679859366351333,
        "mse": 1.158603345429233,
        "rmse": 1.0763843855376354,
        "mbe": -0.05011275159404519,
        "median_ae": 0.35581648349761963,
        "p95_ae": 2.5074573755264282,
        "max_ae": 8.969415485858917,
        "smape": 25.08551949298671,
        "mape_nonzero": 34.649428047383786,
        "wape": 14.382638415670499,
        "nmae_by_mean": 14.382638415670499,
        "nrmse_by_mean": 22.77124973146459,
        "nmbe_by_mean": -1.060150998668453,
        "nmae_by_max": 7.187560928316032,
        "nrmse_by_max": 11.379674586025653,
        "nmbe_by_max": -0.5297984747946098,
        "r2": 0.7730322304476414,
        "pearson_r": 0.8875791594512886,
        "mean_true": 4.726944714195118,
        "mean_pred": 4.676831962601073,
        "mean_abs_true": 4.726944714195118,
        "max_abs_true": 9.458832740783691,
        "sum_abs_true": 98679.69785353728,
        "nonzero_target_count": 20836
      },
      "t+8": {
        "count": 20876,
        "mae": 0.7047394341974466,
        "mse": 1.232915278013454,
        "rmse": 1.1103671816176188,
        "mbe": -0.06164769572501676,
        "median_ae": 0.37160396575927734,
        "p95_ae": 2.594296634197235,
        "max_ae": 9.10402326285839,
        "smape": 25.839567519998347,
        "mape_nonzero": 36.33113266951432,
        "wape": 14.909579447573057,
        "nmae_by_mean": 14.909579447573057,
        "nrmse_by_mean": 23.491104523132776,
        "nmbe_by_mean": -1.3042284461045666,
        "nmae_by_max": 7.450596215311202,
        "nrmse_by_max": 11.738945090233424,
        "nmbe_by_max": -0.6517473922465096,
        "r2": 0.7585069397964392,
        "pearson_r": 0.8818247827707321,
        "mean_true": 4.726755953617205,
        "mean_pred": 4.665108257892188,
        "mean_abs_true": 4.726755953617205,
        "max_abs_true": 9.458832740783691,
        "sum_abs_true": 98675.75728771277,
        "nonzero_target_count": 20836
      },
      "t+9": {
        "count": 20876,
        "mae": 0.7282471005404175,
        "mse": 1.3003129809243437,
        "rmse": 1.1403126680539613,
        "mbe": -0.09833044929086465,
        "median_ae": 0.39276301860809326,
        "p95_ae": 2.6776170432567596,
        "max_ae": 9.149853572249413,
        "smape": 26.57806795767485,
        "mape_nonzero": 37.791337217115654,
        "wape": 15.407517502992574,
        "nmae_by_mean": 15.407517502992574,
        "nrmse_by_mean": 24.12558509177404,
        "nmbe_by_mean": -2.080376451072512,
        "nmae_by_max": 7.699122296564472,
        "nrmse_by_max": 12.055532636043663,
        "nmbe_by_max": -1.039562195310768,
        "r2": 0.7453325404917777,
        "pearson_r": 0.8764295529360421,
        "mean_true": 4.726570003240116,
        "mean_pred": 4.628239553949252,
        "mean_abs_true": 4.726570003240116,
        "max_abs_true": 9.458832740783691,
        "sum_abs_true": 98671.87538764067,
        "nonzero_target_count": 20836
      },
      "t+10": {
        "count": 20876,
        "mae": 0.753321107905463,
        "mse": 1.378448774516161,
        "rmse": 1.174073581389242,
        "mbe": -0.10992909630423428,
        "median_ae": 0.40320461988449097,
        "p95_ae": 2.7441601157188416,
        "max_ae": 9.187969341874123,
        "smape": 27.527505900290127,
        "mape_nonzero": 40.00722253651999,
        "wape": 15.938733521105519,
        "nmae_by_mean": 15.938733521105517,
        "nrmse_by_mean": 24.840995096982617,
        "nmbe_by_mean": -2.3258747880844153,
        "nmae_by_max": 7.964207937173527,
        "nrmse_by_max": 12.412457367249806,
        "nmbe_by_max": -1.1621845878535573,
        "r2": 0.7300392242878866,
        "pearson_r": 0.870360098320831,
        "mean_true": 4.726354869462755,
        "mean_pred": 4.61642577315852,
        "mean_abs_true": 4.726354869462755,
        "max_abs_true": 9.458832740783691,
        "sum_abs_true": 98667.38425490446,
        "nonzero_target_count": 20836
      },
      "t+11": {
        "count": 20876,
        "mae": 0.781122390839895,
        "mse": 1.463698286767178,
        "rmse": 1.2098339914083989,
        "mbe": -0.12863231069730244,
        "median_ae": 0.4210796356201172,
        "p95_ae": 2.823538675904274,
        "max_ae": 9.294675841927528,
        "smape": 28.67207754316817,
        "mape_nonzero": 41.98087004416502,
        "wape": 16.52777616003372,
        "nmae_by_mean": 16.52777616003372,
        "nrmse_by_mean": 25.598889028514215,
        "nmbe_by_mean": -2.7217322958402934,
        "nmae_by_max": 8.258126686942314,
        "nrmse_by_max": 12.790521035348815,
        "nmbe_by_max": -1.3599173832800524,
        "r2": 0.7133520942744687,
        "pearson_r": 0.8640925212493755,
        "mean_true": 4.726119129860609,
        "mean_pred": 4.597486819163307,
        "mean_abs_true": 4.726119129860609,
        "max_abs_true": 9.458832740783691,
        "sum_abs_true": 98662.46295497008,
        "nonzero_target_count": 20836
      },
      "t+12": {
        "count": 20876,
        "mae": 0.8079966858890514,
        "mse": 1.5544399782998468,
        "rmse": 1.2467718228689029,
        "mbe": -0.13470590813116665,
        "median_ae": 0.4356510639190674,
        "p95_ae": 2.8955834358930588,
        "max_ae": 9.452052816748619,
        "smape": 29.898194254980037,
        "mape_nonzero": 43.65347531810412,
        "wape": 17.09701234519299,
        "nmae_by_mean": 17.09701234519299,
        "nrmse_by_mean": 26.381386977811662,
        "nmbe_by_mean": -2.850344084957337,
        "nmae_by_max": 8.542245201199176,
        "nrmse_by_max": 13.18103255482245,
        "nmbe_by_max": -1.4241282388930991,
        "r2": 0.6955764076165807,
        "pearson_r": 0.857973673766456,
        "mean_true": 4.7259525206825295,
        "mean_pred": 4.5912466125513625,
        "mean_abs_true": 4.7259525206825295,
        "max_abs_true": 9.458832740783691,
        "sum_abs_true": 98658.98482176848,
        "nonzero_target_count": 20836
      }
    },
    "mape_note": "MAPE excludes targets with abs(y_true) <= 1e-6 to avoid night-time zero division.",
    "normalization_note": "nmae_by_mean/nrmse_by_mean/nmbe_by_mean use mean(abs(y_true)) as denominator. nmae_by_max/nrmse_by_max/nmbe_by_max use max(abs(y_true)) in the evaluated split/scope as a PV capacity proxy."
  },
  "reported_metrics": {
    "all_timestamps": {
      "count": 551856,
      "mae": 0.34089378776196744,
      "mse": 0.5259404439104236,
      "rmse": 0.7252175148949614,
      "mbe": -0.025230812069316984,
      "median_ae": 0.08489541709423065,
      "p95_ae": 1.6755621954798698,
      "max_ae": 9.452052816748619,
      "smape": 120.0880887552032,
      "mape_nonzero": 32.58752197914547,
      "wape": 15.886406811711499,
      "nmae_by_mean": 15.886406811711499,
      "nrmse_by_mean": 33.79674515114522,
      "nmbe_by_mean": -1.1758118191431859,
      "nmae_by_max": 3.6039731022215262,
      "nrmse_by_max": 7.667093126280136,
      "nmbe_by_max": -0.26674340017166365,
      "r2": 0.9330504134012619,
      "pearson_r": 0.9664615477055892,
      "mean_true": 2.1458205861293926,
      "mean_pred": 2.1205897740600776,
      "mean_abs_true": 2.1458205861293926,
      "max_abs_true": 9.458832740783691,
      "sum_abs_true": 1184183.965379022,
      "nonzero_target_count": 250032
    },
    "daytime_only": {
      "count": 250512,
      "mae": 0.6490520836238525,
      "mse": 1.0982080578595186,
      "rmse": 1.0479542250783278,
      "mbe": -0.05382640878673817,
      "median_ae": 0.32638001441955566,
      "p95_ae": 2.442574441432953,
      "max_ae": 9.452052816748619,
      "smape": 24.01267053416324,
      "mape_nonzero": 32.58752197914547,
      "wape": 13.730580748130347,
      "nmae_by_mean": 13.730580748130347,
      "nrmse_by_mean": 22.16928420820118,
      "nmbe_by_mean": -1.1386880511988247,
      "nmae_by_max": 6.861862360937325,
      "nrmse_by_max": 11.079107261933693,
      "nmbe_by_max": -0.5690597377269883,
      "r2": 0.7848310550782607,
      "pearson_r": 0.8937337779951764,
      "mean_true": 4.727054853176782,
      "mean_pred": 4.673228444390044,
      "mean_abs_true": 4.727054853176782,
      "max_abs_true": 9.458832740783691,
      "sum_abs_true": 1184183.965379022,
      "nonzero_target_count": 250032
    },
    "per_horizon_all": {
      "t+1": {
        "count": 45988,
        "mae": 0.2221193607590747,
        "mse": 0.2396929569624097,
        "rmse": 0.48958447377588443,
        "mbe": -0.010646464968593837,
        "median_ae": 0.06811787188053131,
        "p95_ae": 1.0420467138290406,
        "max_ae": 6.2151408195495605,
        "smape": 116.43580743442948,
        "mape_nonzero": 18.293203965575618,
        "wape": 10.348710163365988,
        "nmae_by_mean": 10.348710163365988,
        "nrmse_by_mean": 22.810113455558778,
        "nmbe_by_mean": -0.4960269102517021,
        "nmae_by_max": 2.3482745371039457,
        "nrmse_by_max": 5.175950217038312,
        "nmbe_by_max": -0.11255580112638451,
        "r2": 0.969492761374168,
        "pearson_r": 0.9847884363026422,
        "mean_true": 2.146348262272995,
        "mean_pred": 2.1357017973044012,
        "mean_abs_true": 2.146348262272995,
        "max_abs_true": 9.458832740783691,
        "sum_abs_true": 98706.2638854105,
        "nonzero_target_count": 20836
      },
      "t+2": {
        "count": 45988,
        "mae": 0.26476528569067137,
        "mse": 0.3399621499214325,
        "rmse": 0.5830627324065846,
        "mbe": -0.01004741365654503,
        "median_ae": 0.07655303180217743,
        "p95_ae": 1.2965894699096687,
        "max_ae": 7.452514290809631,
        "smape": 117.73937099587803,
        "mape_nonzero": 22.643133584872665,
        "wape": 12.336169661328464,
        "nmae_by_mean": 12.336169661328462,
        "nrmse_by_mean": 27.166555356387533,
        "nmbe_by_mean": -0.46813765332323987,
        "nmae_by_max": 2.7991327571432962,
        "nrmse_by_max": 6.164214426718747,
        "nmbe_by_max": -0.10622255337303461,
        "r2": 0.9567297533906927,
        "pearson_r": 0.9783483901582734,
        "mean_true": 2.146251980634313,
        "mean_pred": 2.136204566977768,
        "mean_abs_true": 2.146251980634313,
        "max_abs_true": 9.458832740783691,
        "sum_abs_true": 98701.83608541079,
        "nonzero_target_count": 20836
      },
      "t+3": {
        "count": 45988,
        "mae": 0.2924999344255182,
        "mse": 0.399851728049046,
        "rmse": 0.6323383018994232,
        "mbe": -0.01186072181933222,
        "median_ae": 0.08565092086791992,
        "p95_ae": 1.4242733418941502,
        "max_ae": 8.434280514717102,
        "smape": 118.60914180743387,
        "mape_nonzero": 25.668730730789452,
        "wape": 13.629061726072653,
        "nmae_by_mean": 13.629061726072656,
        "nrmse_by_mean": 29.46386215529811,
        "nmbe_by_mean": -0.5526514394232045,
        "nmae_by_max": 3.0923470415577277,
        "nrmse_by_max": 6.68516210433627,
        "nmbe_by_max": -0.12539308120115383,
        "r2": 0.9491054970315645,
        "pearson_r": 0.9746092939883078,
        "mean_true": 2.1461487247207947,
        "mean_pred": 2.1342880029014624,
        "mean_abs_true": 2.1461487247207947,
        "max_abs_true": 9.458832740783691,
        "sum_abs_true": 98697.08755245991,
        "nonzero_target_count": 20836
      },
      "t+4": {
        "count": 45988,
        "mae": 0.3117035760308293,
        "mse": 0.44087162737448277,
        "rmse": 0.6639816468656967,
        "mbe": -0.01553118750301131,
        "median_ae": 0.08982416987419128,
        "p95_ae": 1.5158710032701497,
        "max_ae": 8.62689220905304,
        "smape": 119.18380053741244,
        "mape_nonzero": 27.418011108400325,
        "wape": 14.524525752673407,
        "nmae_by_mean": 14.524525752673407,
        "nrmse_by_mean": 30.939710901005068,
        "nmbe_by_mean": -0.7237104422400841,
        "nmae_by_max": 3.2953704180311343,
        "nrmse_by_max": 7.019699629562156,
        "nmbe_by_max": -0.1641977179281902,
        "r2": 0.9438827825055461,
        "pearson_r": 0.9720291818372739,
        "mean_true": 2.1460499388316117,
        "mean_pred": 2.1305187513286006,
        "mean_abs_true": 2.1460499388316117,
        "max_abs_true": 9.458832740783691,
        "sum_abs_true": 98692.54458698817,
        "nonzero_target_count": 20836
      },
      "t+5": {
        "count": 45988,
        "mae": 0.3219851997611467,
        "mse": 0.47604585324417786,
        "rmse": 0.6899607621047575,
        "mbe": -0.0111923393503046,
        "median_ae": 0.07579080760478973,
        "p95_ae": 1.5856836795806888,
        "max_ae": 8.384565234184265,
        "smape": 119.60012913695392,
        "mape_nonzero": 30.115139155749794,
        "wape": 15.004431342467484,
        "nmae_by_mean": 15.004431342467484,
        "nrmse_by_mean": 32.15200230220826,
        "nmbe_by_mean": -0.5215602688192467,
        "nmae_by_max": 3.404069070519047,
        "nrmse_by_max": 7.294354187381395,
        "nmbe_by_max": -0.11832685551195488,
        "r2": 0.9394032473940727,
        "pearson_r": 0.9696203008085393,
        "mean_true": 2.1459340404979064,
        "mean_pred": 2.1347417011476013,
        "mean_abs_true": 2.1459340404979064,
        "max_abs_true": 9.458832740783691,
        "sum_abs_true": 98687.21465441771,
        "nonzero_target_count": 20836
      },
      "t+6": {
        "count": 45988,
        "mae": 0.33884271592635296,
        "mse": 0.5128769808684335,
        "rmse": 0.7161542996229469,
        "mbe": -0.018612245918356748,
        "median_ae": 0.07756070792675018,
        "p95_ae": 1.6727999016642587,
        "max_ae": 8.42754477262497,
        "smape": 120.14215024826169,
        "mape_nonzero": 32.49857937155497,
        "wape": 15.79068486984764,
        "nmae_by_mean": 15.79068486984764,
        "nrmse_by_mean": 33.374088720237694,
        "nmbe_by_mean": -0.867364403019241,
        "nmae_by_max": 3.582288906170878,
        "nrmse_by_max": 7.571275645197755,
        "nmbe_by_max": -0.19677106497619146,
        "r2": 0.9347135920368946,
        "pearson_r": 0.9671432511235671,
        "mean_true": 2.14583926358618,
        "mean_pred": 2.127227017667823,
        "mean_abs_true": 2.14583926358618,
        "max_abs_true": 9.458832740783691,
        "sum_abs_true": 98682.85605380125,
        "nonzero_target_count": 20836
      },
      "t+7": {
        "count": 45988,
        "mae": 0.3525632355838088,
        "mse": 0.5517959709744997,
        "rmse": 0.7428297052316228,
        "mbe": -0.020962778489489017,
        "median_ae": 0.07826252281665802,
        "p95_ae": 1.742873154580593,
        "max_ae": 8.969415485858917,
        "smape": 120.57942962828014,
        "mape_nonzero": 34.649428047383786,
        "wape": 16.43061179827782,
        "nmae_by_mean": 16.43061179827782,
        "nrmse_by_mean": 34.6183188915868,
        "nmbe_by_mean": -0.9769347476169477,
        "nmae_by_max": 3.727344010045344,
        "nrmse_by_max": 7.853291474631543,
        "nmbe_by_max": -0.22162119855554385,
        "r2": 0.9297599535352317,
        "pearson_r": 0.9647689576913887,
        "mean_true": 2.1457705891436305,
        "mean_pred": 2.1248078106541413,
        "mean_abs_true": 2.1457705891436305,
        "max_abs_true": 9.458832740783691,
        "sum_abs_true": 98679.69785353728,
        "nonzero_target_count": 20836
      },
      "t+8": {
        "count": 45988,
        "mae": 0.3671346083754966,
        "mse": 0.5895937630693453,
        "rmse": 0.7678500915343732,
        "mbe": -0.02326421548254413,
        "median_ae": 0.08276832103729248,
        "p95_ae": 1.8029488086700447,
        "max_ae": 9.10402326285839,
        "smape": 120.9123235440485,
        "mape_nonzero": 36.33113266951432,
        "wape": 17.110369186976314,
        "nmae_by_mean": 17.11036918697631,
        "nrmse_by_mean": 35.785780601128295,
        "nmbe_by_mean": -1.0842326129727728,
        "nmae_by_max": 3.881394443021713,
        "nrmse_by_max": 8.117810226452473,
        "nmbe_by_max": -0.24595228734974572,
        "r2": 0.9249472702323038,
        "pearson_r": 0.9623876636470085,
        "mean_true": 2.1456849023160993,
        "mean_pred": 2.122420686833555,
        "mean_abs_true": 2.1456849023160993,
        "max_abs_true": 9.458832740783691,
        "sum_abs_true": 98675.75728771277,
        "nonzero_target_count": 20836
      },
      "t+9": {
        "count": 45988,
        "mae": 0.38018792209846236,
        "mse": 0.6243604254782129,
        "rmse": 0.7901648090608775,
        "mbe": -0.03456206402336513,
        "median_ae": 0.08680637180805206,
        "p95_ae": 1.852798950672151,
        "max_ae": 9.149853572249413,
        "smape": 121.2295002883222,
        "mape_nonzero": 37.791337217115654,
        "wape": 17.719418114611095,
        "nmae_by_mean": 17.719418114611095,
        "nrmse_by_mean": 36.82721048559622,
        "nmbe_by_mean": -1.6108340842436286,
        "nmae_by_max": 4.019395759681894,
        "nrmse_by_max": 8.353724298918198,
        "nmbe_by_max": -0.36539459963536225,
        "r2": 0.9205196926104795,
        "pearson_r": 0.9600221788406602,
        "mean_true": 2.1456004911637963,
        "mean_pred": 2.111038427140431,
        "mean_abs_true": 2.1456004911637963,
        "max_abs_true": 9.458832740783691,
        "sum_abs_true": 98671.87538764067,
        "nonzero_target_count": 20836
      },
      "t+10": {
        "count": 45988,
        "mae": 0.3958041065423872,
        "mse": 0.6656770015211455,
        "rmse": 0.8158903121873341,
        "mbe": -0.033548834392092775,
        "median_ae": 0.0964319258928299,
        "p95_ae": 1.9392381608486176,
        "max_ae": 9.187969341874123,
        "smape": 121.67355968670105,
        "mape_nonzero": 40.00722253651999,
        "wape": 18.448081287577583,
        "nmae_by_mean": 18.448081287577583,
        "nrmse_by_mean": 38.02792985768856,
        "nmbe_by_mean": -1.5636816640822948,
        "nmae_by_max": 4.184492076234701,
        "nrmse_by_max": 8.625697636765011,
        "nmbe_by_max": -0.3546826052588933,
        "r2": 0.9152555993077105,
        "pearson_r": 0.9573409830826033,
        "mean_true": 2.1455028323672365,
        "mean_pred": 2.111953997975143,
        "mean_abs_true": 2.1455028323672365,
        "max_abs_true": 9.458832740783691,
        "sum_abs_true": 98667.38425490446,
        "nonzero_target_count": 20836
      },
      "t+11": {
        "count": 45988,
        "mae": 0.4121485652193041,
        "mse": 0.7107707254331187,
        "rmse": 0.8430721946744055,
        "mbe": -0.04727969345278535,
        "median_ae": 0.09739001095294952,
        "p95_ae": 2.031183815002442,
        "max_ae": 9.294675841927528,
        "smape": 122.19920634705078,
        "mape_nonzero": 41.98087004416502,
        "wape": 19.21084032329092,
        "nmae_by_mean": 19.21084032329092,
        "nrmse_by_mean": 39.29681352712823,
        "nmbe_by_mean": -2.2037748474808003,
        "nmae_by_max": 4.357287801931852,
        "nrmse_by_max": 8.913068005096731,
        "nmbe_by_max": -0.4998470186382436,
        "r2": 0.9095093419347605,
        "pearson_r": 0.9545769758337588,
        "mean_true": 2.145395819669698,
        "mean_pred": 2.0981161262169126,
        "mean_abs_true": 2.145395819669698,
        "max_abs_true": 9.458832740783691,
        "sum_abs_true": 98662.46295497008,
        "nonzero_target_count": 20836
      },
      "t+12": {
        "count": 45988,
        "mae": 0.4309709427305568,
        "mse": 0.7597861440287803,
        "rmse": 0.8716571252670285,
        "mbe": -0.06526178577538362,
        "median_ae": 0.10641534626483917,
        "p95_ae": 2.114285838603974,
        "max_ae": 9.452052816748619,
        "smape": 122.7526454076665,
        "mape_nonzero": 43.65347531810412,
        "wape": 20.088886734540775,
        "nmae_by_mean": 20.088886734540775,
        "nrmse_by_mean": 40.630630802857645,
        "nmbe_by_mean": -3.042053402090281,
        "nmae_by_max": 4.556280405216782,
        "nrmse_by_max": 9.215271579004677,
        "nmbe_by_max": -0.6899560185052653,
        "r2": 0.9032637439506359,
        "pearson_r": 0.9519006006377184,
        "mean_true": 2.145320188348449,
        "mean_pred": 2.0800584025730653,
        "mean_abs_true": 2.145320188348449,
        "max_abs_true": 9.458832740783691,
        "sum_abs_true": 98658.98482176848,
        "nonzero_target_count": 20836
      }
    },
    "per_horizon_daytime": {
      "t+1": {
        "count": 20876,
        "mae": 0.4190072853721092,
        "mse": 0.5071389368223871,
        "rmse": 0.7121368806784178,
        "mbe": 0.010936700260222674,
        "median_ae": 0.20778656005859375,
        "p95_ae": 1.605574607849121,
        "max_ae": 6.2151408195495605,
        "smape": 15.966491775331118,
        "mape_nonzero": 18.293203965575618,
        "wape": 8.861844978331765,
        "nmae_by_mean": 8.861844978331765,
        "nrmse_by_mean": 15.061424610601676,
        "nmbe_by_mean": 0.23130705757180933,
        "nmae_by_max": 4.429799076216599,
        "nrmse_by_max": 7.5288029738372915,
        "nmbe_by_max": 0.11562420607213884,
        "r2": 0.9005701713934109,
        "pearson_r": 0.949658310644502,
        "mean_true": 4.728217277515353,
        "mean_pred": 4.739153977775575,
        "mean_abs_true": 4.728217277515353,
        "max_abs_true": 9.458832740783691,
        "sum_abs_true": 98706.2638854105,
        "nonzero_target_count": 20836
      },
      "t+2": {
        "count": 20876,
        "mae": 0.5038663900838779,
        "mse": 0.7203653871382947,
        "rmse": 0.8487434165507822,
        "mbe": -0.0005171155979022423,
        "median_ae": 0.24351632595062256,
        "p95_ae": 1.9336585998535156,
        "max_ae": 7.452514290809631,
        "smape": 18.819874433991547,
        "mape_nonzero": 22.643133584872665,
        "wape": 10.65706087806589,
        "nmae_by_mean": 10.657060878065892,
        "nrmse_by_mean": 17.951406241907893,
        "nmbe_by_mean": -0.010937289162954968,
        "nmae_by_max": 5.326940478726883,
        "nrmse_by_max": 8.973024894406382,
        "nmbe_by_max": -0.00546701281303551,
        "r2": 0.8587829124766846,
        "pearson_r": 0.9284070654149341,
        "mean_true": 4.728005177496206,
        "mean_pred": 4.7274880618983035,
        "mean_abs_true": 4.728005177496206,
        "max_abs_true": 9.458832740783691,
        "sum_abs_true": 98701.83608541079,
        "nonzero_target_count": 20836
      },
      "t+3": {
        "count": 20876,
        "mae": 0.5531906242550052,
        "mse": 0.846905842909092,
        "rmse": 0.9202748735617484,
        "mbe": 0.002126734537498704,
        "median_ae": 0.2664567232131958,
        "p95_ae": 2.1074156761169434,
        "max_ae": 8.434280514717102,
        "smape": 20.731472217970342,
        "mape_nonzero": 25.668730730789452,
        "wape": 11.7008594258764,
        "nmae_by_mean": 11.700859425876398,
        "nrmse_by_mean": 19.465273734915016,
        "nmbe_by_mean": 0.044983809862904484,
        "nmae_by_max": 5.848402645601404,
        "nrmse_by_max": 9.729264686051538,
        "nmbe_by_max": 0.02248411189605725,
        "r2": 0.8339977442151933,
        "pearson_r": 0.9161992225091784,
        "mean_true": 4.727777713760295,
        "mean_pred": 4.729904448297793,
        "mean_abs_true": 4.727777713760295,
        "max_abs_true": 9.458832740783691,
        "sum_abs_true": 98697.08755245991,
        "nonzero_target_count": 20836
      },
      "t+4": {
        "count": 20876,
        "mae": 0.5880562554339421,
        "mse": 0.9317673259419361,
        "rmse": 0.965280956997462,
        "mbe": -0.005219138783295248,
        "median_ae": 0.29205989837646484,
        "p95_ae": 2.202492117881775,
        "max_ae": 8.62689220905304,
        "smape": 21.992021793201637,
        "mape_nonzero": 27.418011108400325,
        "wape": 12.43889539966072,
        "nmae_by_mean": 12.43889539966072,
        "nrmse_by_mean": 20.41816364408117,
        "nmbe_by_mean": -0.11039814779933886,
        "nmae_by_max": 6.217006596368042,
        "nrmse_by_max": 10.205074806275576,
        "nmbe_by_max": -0.05517740852728967,
        "r2": 0.8173870096219722,
        "pearson_r": 0.9082534234443906,
        "mean_true": 4.727560097096578,
        "mean_pred": 4.722340958313283,
        "mean_abs_true": 4.727560097096578,
        "max_abs_true": 9.458832740783691,
        "sum_abs_true": 98692.54458698817,
        "nonzero_target_count": 20836
      },
      "t+5": {
        "count": 20876,
        "mae": 0.6180898432043754,
        "mse": 1.0044803316620616,
        "rmse": 1.002237662264825,
        "mbe": -0.020440783952041294,
        "median_ae": 0.30850958824157715,
        "p95_ae": 2.3009897470474243,
        "max_ae": 8.384565234184265,
        "smape": 22.92765826557724,
        "mape_nonzero": 30.115139155749794,
        "wape": 13.074888790730432,
        "nmae_by_mean": 13.074888790730432,
        "nrmse_by_mean": 21.201037551528348,
        "nmbe_by_mean": -0.43239826686476646,
        "nmae_by_max": 6.534525560848061,
        "nrmse_by_max": 10.595785862070194,
        "nmbe_by_max": -0.21610260496421163,
        "r2": 0.8031616605296605,
        "pearson_r": 0.9010194385337532,
        "mean_true": 4.727304783216024,
        "mean_pred": 4.706863999263982,
        "mean_abs_true": 4.727304783216024,
        "max_abs_true": 9.458832740783691,
        "sum_abs_true": 98687.21465441771,
        "nonzero_target_count": 20836
      },
      "t+6": {
        "count": 20876,
        "mae": 0.6511285194133138,
        "mse": 1.0794202258902335,
        "rmse": 1.0389515031464334,
        "mbe": -0.0494450901627106,
        "median_ae": 0.33936265110969543,
        "p95_ae": 2.39077827334404,
        "max_ae": 8.42754477262497,
        "smape": 24.113595254788798,
        "mape_nonzero": 32.49857937155497,
        "wape": 13.774387482119026,
        "nmae_by_mean": 13.77438748211903,
        "nrmse_by_mean": 21.97864193134029,
        "nmbe_by_mean": -1.0459929348558672,
        "nmae_by_max": 6.883814707980195,
        "nrmse_by_max": 10.983929324247182,
        "nmbe_by_max": -0.5227398720089211,
        "r2": 0.7885062151669776,
        "pearson_r": 0.8940548985695511,
        "mean_true": 4.7270959979786,
        "mean_pred": 4.677650907815889,
        "mean_abs_true": 4.7270959979786,
        "max_abs_true": 9.458832740783691,
        "sum_abs_true": 98682.85605380125,
        "nonzero_target_count": 20836
      },
      "t+7": {
        "count": 20876,
        "mae": 0.679859366351333,
        "mse": 1.158603345429233,
        "rmse": 1.0763843855376354,
        "mbe": -0.05011275159404519,
        "median_ae": 0.35581648349761963,
        "p95_ae": 2.5074573755264282,
        "max_ae": 8.969415485858917,
        "smape": 25.08551949298671,
        "mape_nonzero": 34.649428047383786,
        "wape": 14.382638415670499,
        "nmae_by_mean": 14.382638415670499,
        "nrmse_by_mean": 22.77124973146459,
        "nmbe_by_mean": -1.060150998668453,
        "nmae_by_max": 7.187560928316032,
        "nrmse_by_max": 11.379674586025653,
        "nmbe_by_max": -0.5297984747946098,
        "r2": 0.7730322304476414,
        "pearson_r": 0.8875791594512886,
        "mean_true": 4.726944714195118,
        "mean_pred": 4.676831962601073,
        "mean_abs_true": 4.726944714195118,
        "max_abs_true": 9.458832740783691,
        "sum_abs_true": 98679.69785353728,
        "nonzero_target_count": 20836
      },
      "t+8": {
        "count": 20876,
        "mae": 0.7047394341974466,
        "mse": 1.232915278013454,
        "rmse": 1.1103671816176188,
        "mbe": -0.06164769572501676,
        "median_ae": 0.37160396575927734,
        "p95_ae": 2.594296634197235,
        "max_ae": 9.10402326285839,
        "smape": 25.839567519998347,
        "mape_nonzero": 36.33113266951432,
        "wape": 14.909579447573057,
        "nmae_by_mean": 14.909579447573057,
        "nrmse_by_mean": 23.491104523132776,
        "nmbe_by_mean": -1.3042284461045666,
        "nmae_by_max": 7.450596215311202,
        "nrmse_by_max": 11.738945090233424,
        "nmbe_by_max": -0.6517473922465096,
        "r2": 0.7585069397964392,
        "pearson_r": 0.8818247827707321,
        "mean_true": 4.726755953617205,
        "mean_pred": 4.665108257892188,
        "mean_abs_true": 4.726755953617205,
        "max_abs_true": 9.458832740783691,
        "sum_abs_true": 98675.75728771277,
        "nonzero_target_count": 20836
      },
      "t+9": {
        "count": 20876,
        "mae": 0.7282471005404175,
        "mse": 1.3003129809243437,
        "rmse": 1.1403126680539613,
        "mbe": -0.09833044929086465,
        "median_ae": 0.39276301860809326,
        "p95_ae": 2.6776170432567596,
        "max_ae": 9.149853572249413,
        "smape": 26.57806795767485,
        "mape_nonzero": 37.791337217115654,
        "wape": 15.407517502992574,
        "nmae_by_mean": 15.407517502992574,
        "nrmse_by_mean": 24.12558509177404,
        "nmbe_by_mean": -2.080376451072512,
        "nmae_by_max": 7.699122296564472,
        "nrmse_by_max": 12.055532636043663,
        "nmbe_by_max": -1.039562195310768,
        "r2": 0.7453325404917777,
        "pearson_r": 0.8764295529360421,
        "mean_true": 4.726570003240116,
        "mean_pred": 4.628239553949252,
        "mean_abs_true": 4.726570003240116,
        "max_abs_true": 9.458832740783691,
        "sum_abs_true": 98671.87538764067,
        "nonzero_target_count": 20836
      },
      "t+10": {
        "count": 20876,
        "mae": 0.753321107905463,
        "mse": 1.378448774516161,
        "rmse": 1.174073581389242,
        "mbe": -0.10992909630423428,
        "median_ae": 0.40320461988449097,
        "p95_ae": 2.7441601157188416,
        "max_ae": 9.187969341874123,
        "smape": 27.527505900290127,
        "mape_nonzero": 40.00722253651999,
        "wape": 15.938733521105519,
        "nmae_by_mean": 15.938733521105517,
        "nrmse_by_mean": 24.840995096982617,
        "nmbe_by_mean": -2.3258747880844153,
        "nmae_by_max": 7.964207937173527,
        "nrmse_by_max": 12.412457367249806,
        "nmbe_by_max": -1.1621845878535573,
        "r2": 0.7300392242878866,
        "pearson_r": 0.870360098320831,
        "mean_true": 4.726354869462755,
        "mean_pred": 4.61642577315852,
        "mean_abs_true": 4.726354869462755,
        "max_abs_true": 9.458832740783691,
        "sum_abs_true": 98667.38425490446,
        "nonzero_target_count": 20836
      },
      "t+11": {
        "count": 20876,
        "mae": 0.781122390839895,
        "mse": 1.463698286767178,
        "rmse": 1.2098339914083989,
        "mbe": -0.12863231069730244,
        "median_ae": 0.4210796356201172,
        "p95_ae": 2.823538675904274,
        "max_ae": 9.294675841927528,
        "smape": 28.67207754316817,
        "mape_nonzero": 41.98087004416502,
        "wape": 16.52777616003372,
        "nmae_by_mean": 16.52777616003372,
        "nrmse_by_mean": 25.598889028514215,
        "nmbe_by_mean": -2.7217322958402934,
        "nmae_by_max": 8.258126686942314,
        "nrmse_by_max": 12.790521035348815,
        "nmbe_by_max": -1.3599173832800524,
        "r2": 0.7133520942744687,
        "pearson_r": 0.8640925212493755,
        "mean_true": 4.726119129860609,
        "mean_pred": 4.597486819163307,
        "mean_abs_true": 4.726119129860609,
        "max_abs_true": 9.458832740783691,
        "sum_abs_true": 98662.46295497008,
        "nonzero_target_count": 20836
      },
      "t+12": {
        "count": 20876,
        "mae": 0.8079966858890514,
        "mse": 1.5544399782998468,
        "rmse": 1.2467718228689029,
        "mbe": -0.13470590813116665,
        "median_ae": 0.4356510639190674,
        "p95_ae": 2.8955834358930588,
        "max_ae": 9.452052816748619,
        "smape": 29.898194254980037,
        "mape_nonzero": 43.65347531810412,
        "wape": 17.09701234519299,
        "nmae_by_mean": 17.09701234519299,
        "nrmse_by_mean": 26.381386977811662,
        "nmbe_by_mean": -2.850344084957337,
        "nmae_by_max": 8.542245201199176,
        "nrmse_by_max": 13.18103255482245,
        "nmbe_by_max": -1.4241282388930991,
        "r2": 0.6955764076165807,
        "pearson_r": 0.857973673766456,
        "mean_true": 4.7259525206825295,
        "mean_pred": 4.5912466125513625,
        "mean_abs_true": 4.7259525206825295,
        "max_abs_true": 9.458832740783691,
        "sum_abs_true": 98658.98482176848,
        "nonzero_target_count": 20836
      }
    },
    "mape_note": "MAPE excludes targets with abs(y_true) <= 1e-6 to avoid night-time zero division.",
    "normalization_note": "nmae_by_mean/nrmse_by_mean/nmbe_by_mean use mean(abs(y_true)) as denominator. nmae_by_max/nrmse_by_max/nmbe_by_max use max(abs(y_true)) in the evaluated split/scope as a PV capacity proxy."
  },
  "test_metrics": null,
  "history": [
    {
      "epoch": 1,
      "train_loss": 0.09254973128609505,
      "validation_loss": 0.08308175997326465
    },
    {
      "epoch": 2,
      "train_loss": 0.0741902491390311,
      "validation_loss": 0.0837118086317501
    },
    {
      "epoch": 3,
      "train_loss": 0.0699880677187577,
      "validation_loss": 0.07968656697866895
    },
    {
      "epoch": 4,
      "train_loss": 0.06842664591453752,
      "validation_loss": 0.07717056208617636
    },
    {
      "epoch": 5,
      "train_loss": 0.06578620710901366,
      "validation_loss": 0.0746666309274441
    },
    {
      "epoch": 6,
      "train_loss": 0.06403657552825277,
      "validation_loss": 0.07692543511789507
    },
    {
      "epoch": 7,
      "train_loss": 0.0627300761319447,
      "validation_loss": 0.078211501092905
    },
    {
      "epoch": 8,
      "train_loss": 0.061752139263218556,
      "validation_loss": 0.07783231322693365
    },
    {
      "epoch": 9,
      "train_loss": 0.06044287091353874,
      "validation_loss": 0.07606946927467516
    },
    {
      "epoch": 10,
      "train_loss": 0.060272963648656884,
      "validation_loss": 0.07355696771396725
    },
    {
      "epoch": 11,
      "train_loss": 0.058813210062539534,
      "validation_loss": 0.07302265298503843
    },
    {
      "epoch": 12,
      "train_loss": 0.05791315665616937,
      "validation_loss": 0.07598562842897434
    },
    {
      "epoch": 13,
      "train_loss": 0.057351137401293106,
      "validation_loss": 0.07193975893461144
    },
    {
      "epoch": 14,
      "train_loss": 0.056107434899360535,
      "validation_loss": 0.07248837927399822
    },
    {
      "epoch": 15,
      "train_loss": 0.05555344419477244,
      "validation_loss": 0.07191322105376349
    },
    {
      "epoch": 16,
      "train_loss": 0.05491835566396321,
      "validation_loss": 0.07287254538671795
    },
    {
      "epoch": 17,
      "train_loss": 0.05424226745393358,
      "validation_loss": 0.07822812524402781
    },
    {
      "epoch": 18,
      "train_loss": 0.0536981721466052,
      "validation_loss": 0.07400312482521916
    },
    {
      "epoch": 19,
      "train_loss": 0.053854560719256164,
      "validation_loss": 0.07215189978982088
    },
    {
      "epoch": 20,
      "train_loss": 0.05268444662043856,
      "validation_loss": 0.07438672873129981
    },
    {
      "epoch": 21,
      "train_loss": 0.0526302886223206,
      "validation_loss": 0.0747443737840895
    },
    {
      "epoch": 22,
      "train_loss": 0.05190888835216026,
      "validation_loss": 0.07224161874036629
    },
    {
      "epoch": 23,
      "train_loss": 0.051492090724883435,
      "validation_loss": 0.07525361960566189
    },
    {
      "epoch": 24,
      "train_loss": 0.0508849127105703,
      "validation_loss": 0.07098969142633141
    },
    {
      "epoch": 25,
      "train_loss": 0.050764839864925804,
      "validation_loss": 0.07146801609009323
    },
    {
      "epoch": 26,
      "train_loss": 0.0503953936574939,
      "validation_loss": 0.07252164387716332
    },
    {
      "epoch": 27,
      "train_loss": 0.05000513656890236,
      "validation_loss": 0.07516237257271739
    },
    {
      "epoch": 28,
      "train_loss": 0.050478851463580755,
      "validation_loss": 0.06795470447834827
    },
    {
      "epoch": 29,
      "train_loss": 0.049314522290092005,
      "validation_loss": 0.07236397502165925
    },
    {
      "epoch": 30,
      "train_loss": 0.04843710660096727,
      "validation_loss": 0.07336747969410885
    },
    {
      "epoch": 31,
      "train_loss": 0.04897107175511992,
      "validation_loss": 0.06959912620268928
    },
    {
      "epoch": 32,
      "train_loss": 0.04928561584156047,
      "validation_loss": 0.07062406212030914
    },
    {
      "epoch": 33,
      "train_loss": 0.04849729291954255,
      "validation_loss": 0.07218754788120652
    },
    {
      "epoch": 34,
      "train_loss": 0.04844184152749732,
      "validation_loss": 0.06906918268278954
    },
    {
      "epoch": 35,
      "train_loss": 0.04734949657841465,
      "validation_loss": 0.07048829745776113
    },
    {
      "epoch": 36,
      "train_loss": 0.047182397705482,
      "validation_loss": 0.07129393196148036
    },
    {
      "epoch": 37,
      "train_loss": 0.047208117983803505,
      "validation_loss": 0.0714639286579567
    },
    {
      "epoch": 38,
      "train_loss": 0.046902511804562626,
      "validation_loss": 0.07167253450150635
    },
    {
      "epoch": 39,
      "train_loss": 0.04672222439588114,
      "validation_loss": 0.07076170270713976
    },
    {
      "epoch": 40,
      "train_loss": 0.04749748973033137,
      "validation_loss": 0.07342507761237321
    },
    {
      "epoch": 41,
      "train_loss": 0.04622843740653607,
      "validation_loss": 0.0725261158728408
    },
    {
      "epoch": 42,
      "train_loss": 0.04745041544368582,
      "validation_loss": 0.07007378801068485
    },
    {
      "epoch": 43,
      "train_loss": 0.04576994273453473,
      "validation_loss": 0.06827948938592479
    },
    {
      "epoch": 44,
      "train_loss": 0.046618315617513534,
      "validation_loss": 0.06967976142230466
    },
    {
      "epoch": 45,
      "train_loss": 0.04623291517761196,
      "validation_loss": 0.06938746896257765
    },
    {
      "epoch": 46,
      "train_loss": 0.045793632418857026,
      "validation_loss": 0.06635957703320364
    },
    {
      "epoch": 47,
      "train_loss": 0.045272481177670645,
      "validation_loss": 0.07063793890620333
    },
    {
      "epoch": 48,
      "train_loss": 0.044403973069682155,
      "validation_loss": 0.07284198023758846
    },
    {
      "epoch": 49,
      "train_loss": 0.04527724360242228,
      "validation_loss": 0.06955238065988836
    },
    {
      "epoch": 50,
      "train_loss": 0.044976519675087964,
      "validation_loss": 0.07074206771195062
    },
    {
      "epoch": 51,
      "train_loss": 0.04406213358721262,
      "validation_loss": 0.0683699517878982
    },
    {
      "epoch": 52,
      "train_loss": 0.04419056719083321,
      "validation_loss": 0.07355957562329772
    },
    {
      "epoch": 53,
      "train_loss": 0.04443588430435148,
      "validation_loss": 0.07164198106517128
    },
    {
      "epoch": 54,
      "train_loss": 0.04425321516239816,
      "validation_loss": 0.06753141907459072
    },
    {
      "epoch": 55,
      "train_loss": 0.04488190452195287,
      "validation_loss": 0.06744345676074634
    },
    {
      "epoch": 56,
      "train_loss": 0.04297039974326135,
      "validation_loss": 0.070644717418059
    },
    {
      "epoch": 57,
      "train_loss": 0.04367551053812109,
      "validation_loss": 0.07380676832008276
    },
    {
      "epoch": 58,
      "train_loss": 0.04370617034701399,
      "validation_loss": 0.07145351610780373
    },
    {
      "epoch": 59,
      "train_loss": 0.04329207692407682,
      "validation_loss": 0.06660500981022774
    },
    {
      "epoch": 60,
      "train_loss": 0.04300104343130454,
      "validation_loss": 0.07029300909177724
    },
    {
      "epoch": 61,
      "train_loss": 0.04287354061120948,
      "validation_loss": 0.06899602065342239
    },
    {
      "epoch": 62,
      "train_loss": 0.04361251069605776,
      "validation_loss": 0.0669577589437959
    },
    {
      "epoch": 63,
      "train_loss": 0.04386547738706119,
      "validation_loss": 0.0681480510487276
    },
    {
      "epoch": 64,
      "train_loss": 0.04257703065726968,
      "validation_loss": 0.06894288811254043
    },
    {
      "epoch": 65,
      "train_loss": 0.0437174689843576,
      "validation_loss": 0.07384755552664621
    },
    {
      "epoch": 66,
      "train_loss": 0.042809422371096834,
      "validation_loss": 0.0669195691694371
    }
  ],
  "checkpoint_path": "/home/lunalhx/projects/CiTransformer/checkpoints/tuning/itransformer/standard/pred_len_12/s2_ff4x_pl12_lr0p001_bs128_dm128_ff512_el2_do0p1_wd1e-05_actgelu_nh4_fac5/best_model.pth"
}